README.md
setup.py
rafael/__init__.py
rafael.egg-info/PKG-INFO
rafael.egg-info/SOURCES.txt
rafael.egg-info/dependency_links.txt
rafael.egg-info/top_level.txt