Metadata-Version: 2.1
Name: rafael
Version: 0.0.1
Summary: Um pacote para meu tutorial
Home-page: UNKNOWN
Author: Rafael
Author-email: rafa@rayes.com
License: UNKNOWN
Platform: UNKNOWN
Classifier: Programming Language :: Python :: 3
Classifier: License :: OSI Approved :: MIT License
Classifier: Operating System :: OS Independent
